hoatzin/__init__.py
hoatzin/_version.py
hoatzin/evolve.py
hoatzin/hoatzin_exceptions.py
hoatzin/py.typed
hoatzin/tests/__init__.py
hoatzin/tests/test_hoatzin.py
idptools_hoatzin-0.12.dist-info/LICENSE
idptools_hoatzin-0.12.dist-info/METADATA
idptools_hoatzin-0.12.dist-info/WHEEL
idptools_hoatzin-0.12.dist-info/top_level.txt
idptools_hoatzin-0.12.dist-info/RECORD
