Metadata-Version: 2.1
Name: idptools-hoatzin
Version: 0.12
Summary: A Python package for DNA-based evolution of protien sequences. Holistic apprOach for SequAnces To underZtand evolutIoN.
Author-email: Ryan Emenecker - Holehouse Lab <remenecker@wustl.edu>
License: MIT
Classifier: License :: OSI Approved :: MIT License
Classifier: Programming Language :: Python :: 3
Requires-Python: >=3.8
License-File: LICENSE
Provides-Extra: test
Requires-Dist: pytest >=6.1.2 ; extra == 'test'
Requires-Dist: pytest-runner ; extra == 'test'
